LICENSE.txt
README.rst
setup.py
src/volworld_aws_api_common/__init__.py
src/volworld_aws_api_common.egg-info/PKG-INFO
src/volworld_aws_api_common.egg-info/SOURCES.txt
src/volworld_aws_api_common.egg-info/dependency_links.txt
src/volworld_aws_api_common.egg-info/requires.txt
src/volworld_aws_api_common.egg-info/top_level.txt
src/volworld_aws_api_common/api/AA.py
src/volworld_aws_api_common/api/ApiUrl.py
src/volworld_aws_api_common/api/Aws.py
src/volworld_aws_api_common/api/FrontEndUrl.py
src/volworld_aws_api_common/api/__init__.py
src/volworld_aws_api_common/api/dom_id.py
src/volworld_aws_api_common/api/enum/ErrorCode.py
src/volworld_aws_api_common/api/enum/HttpStatus.py
src/volworld_aws_api_common/api/enum/ProjectModeType.py
src/volworld_aws_api_common/api/enum/QueryModeType.py
src/volworld_aws_api_common/api/enum/__init__.py
src/volworld_aws_api_common/api/url/__init__.py
src/volworld_aws_api_common/api/url/accountUrl.py
src/volworld_aws_api_common/api/url/authUrl.py
src/volworld_aws_api_common/ct/ServerCT.py
src/volworld_aws_api_common/ct/__init__.py
src/volworld_aws_api_common/steps/__init__.py
src/volworld_aws_api_common/steps/brower_common.py
src/volworld_aws_api_common/steps/button_common.py
src/volworld_aws_api_common/steps/input_common.py
src/volworld_aws_api_common/steps/mock_common.py
src/volworld_aws_api_common/steps/pages_common.py
src/volworld_aws_api_common/steps/row_common.py
src/volworld_aws_api_common/steps/selenium_common.py
src/volworld_aws_api_common/steps/user_common.py
src/volworld_aws_api_common/steps/wait_common.py
src/volworld_aws_api_common/test/ProjectMode.py
src/volworld_aws_api_common/test/QueryMode.py
src/volworld_aws_api_common/test/UserPool.py
src/volworld_aws_api_common/test/__init__.py
src/volworld_aws_api_common/test/request.py
src/volworld_aws_api_common/test/api/OAPI.py
src/volworld_aws_api_common/test/api/OpenApiValidation.py
src/volworld_aws_api_common/test/api/__init__.py
src/volworld_aws_api_common/test/api/request_open_api_validation.py
src/volworld_aws_api_common/test/aws/ATestRequest.py
src/volworld_aws_api_common/test/aws/__init__.py
src/volworld_aws_api_common/test/aws/url.py
src/volworld_aws_api_common/test/aws/request/__init__.py
