Metadata-Version: 2.1
Name: volworld_aws_api_common
Version: 0.1.188
Home-page: 
Author: Che-Wri, Chang
Author-email: gobidesert.mf@gmail.com
License: MIT
Keywords: volworld
License-File: LICENSE.txt
Requires-Dist: aenum
Requires-Dist: volworld_common
